pursuitlib_sso/__init__.py
pursuitlib_sso/admin.py
pursuitlib_sso/apps.py
pursuitlib_sso/models.py
pursuitlib_sso/tests.py
pursuitlib_sso/urls.py
pursuitlib_sso/views.py
pursuitlib_sso/migrations/__init__.py
pursuitlib_sso/templates/pursuitlib/sso/saml2-metadata.xml
pursuitlib_sso/templatetags/__init__.py
pursuitlib_sso/templatetags/pursuitlib_sso.py
pursuitlib_sso-0.2.0.dist-info/METADATA
pursuitlib_sso-0.2.0.dist-info/WHEEL
pursuitlib_sso-0.2.0.dist-info/top_level.txt
pursuitlib_sso-0.2.0.dist-info/RECORD
