Metadata-Version: 2.1
Name: pursuitlib-sso
Version: 0.2.0
Summary: Provides SSO functions for Django
Home-page: https://gitlab.com/frPursuit/pursuitlib-python
Author: Pursuit
Author-email: fr.pursuit@gmail.com
License: All rights reserved
Platform: UNKNOWN
Classifier: Programming Language :: Python :: 3
Classifier: Operating System :: OS Independent
Requires-Python: >=3.7
Requires-Dist: pursuitlib-django
Requires-Dist: pysaml2
